mingw_ldd/__init__.py
mingw_ldd/__main__.py
mingw_ldd/__version__.py
mingw_ldd/mingw_ldd.py
mingw_ldd-0.2.1.dist-info/LICENSE
mingw_ldd-0.2.1.dist-info/METADATA
mingw_ldd-0.2.1.dist-info/WHEEL
mingw_ldd-0.2.1.dist-info/entry_points.txt
mingw_ldd-0.2.1.dist-info/top_level.txt
mingw_ldd-0.2.1.dist-info/RECORD
